ape_roll/__init__.py
ape_roll/client.py
ape_roll/utils.py
ape_roll-0.0.3.dist-info/LICENSE
ape_roll-0.0.3.dist-info/WHEEL
ape_roll-0.0.3.dist-info/METADATA
ape_roll-0.0.3.dist-info/RECORD
